{"id": "10354", "title": "True Crime", "release_date": "1999-03-19", "overview": "Boozer, skirt chaser, careless father. You could create your own list of reporter Steve Everett's faults but there's no time. A San Quentin Death Row prisoner is slated to die at midnight – a man Everett has suddenly realized is innocent.", "poster_path": "/xo48IGurAJOJfG29Vp32JglZGPk.jpg", "budget": "0", "genres": ["Crime", "Drama"], "directors": ["Clint Eastwood"], "actors": ["Clint Eastwood", "Isaiah Washington", "Lisa Gay Hamilton", "James Woods", "Denis Leary"]}