{"id": "118640", "title": "Love and Other Troubles", "release_date": "2012-01-01", "overview": "Ville, 25, is a downbeat former child star who's successfully avoided his womanizing rock 'n' roll dad for years. Everything changes when his dad moves into his flat and they both fall in love with the same American line-dancing teacher.", "poster_path": "/amiJeHDIIThZjjlitIit8x0CPPR.jpg", "budget": "0", "genres": ["Comedy", "Romance"], "vote_average": "5.9", "vote_count": "7", "directors": ["Samuli Valkama"], "actors": ["Emilie de Ravin", "Ville Virtanen", "Tommi Korpela", "Jussi Nikkilä", "Jessica Grabowsky"]}