{"id": "12095", "title": "From Dusk Till Dawn 2: Texas Blood Money", "release_date": "1999-03-16", "overview": "A gang of bank-robbing misfits heads to Mexico with the blueprints for the perfect million-dollar heist, but when one of the crooks wanders into the wrong bar... and crosses the wrong vampire... the thieving cohorts develop a thirst for blood!", "poster_path": "/d7bo08grzk9ZYV5W6hatIEszbfZ.jpg", "budget": "5000000", "genres": ["Crime", "Action", "Horror", "Thriller"], "vote_average": "4.4", "vote_count": "114", "directors": ["Scott Spiegel"], "actors": ["Robert Patrick", "Duane Whitaker", "Bo Hopkins", "Muse Watson", "Brett Harrelson"]}