{"id": "139302", "title": "The Bitter Buddha", "release_date": "2012-06-15", "overview": "The Documentary takes an unconventional journey through the life of one of America's most original comedic voices. Eddie Pepitone, \"The Bitter Buddha\", is looked at in this portrait of creativity, enlightenment and rage.", "poster_path": "/caqIC68vRZJzHtxQnRlF4EVoMDi.jpg", "budget": "250000", "genres": ["Documentary"], "directors": ["Steven Feinartz"], "actors": ["Zach Galifianakis", "Sarah Silverman", "Patton Oswalt", "Sean Conroy", "Paul Provenza"]}