{"id": "140818", "title": "Ragnarok", "release_date": "2013-11-11", "overview": "Archaeologist Sigurd Svendsen discovers that the Oseberg ship hides a secret from the Viking Age. Along with his two children put Sigurd out on a quest to find the truth. The mystery leads them into \"No Man's Land\" between Norway and Russia where no man traveling in modern times. Old runes take on new meaning when the secret they uncover is more frightening than anyone could have imagined.", "poster_path": "/wzth1phazWxFEFYTsr8pAYlDvOw.jpg", "budget": "6500000", "genres": ["Action", "Adventure"], "directors": ["Mikkel Brænne Sandemose"], "actors": ["Pål Sverre Hagen", "Nicolai Cleve Broch", "Bjørn Sundquist", "Sofia Helin", "Maria Annette Tanderød Berglyd"]}