{"id": "14346", "title": "Blackballed: The Bobby Dukes Story", "release_date": "2004-01-01", "overview": "Caught cheating and banned for ten years, Bobby Dukes, paintball's first superstar, returns to reclaim his title and erase the memory of his tainted past.", "poster_path": "/wIBqanAzE23sm6x15r8DOl0fMFQ.jpg", "budget": "0", "genres": ["Comedy"], "vote_average": "5.5", "vote_count": "5", "directors": ["Brant Sersen"], "actors": ["Rob Corddry", "Paul Scheer", "Rob Riggle", "Rob Huebel", "Dannah Feinglass Phirman"]}