{"id": "157724", "title": "The Crazy Bunch", "release_date": "1974-04-27", "overview": "Tricky Dicky is after a gold treasure with his companion. He tracks the treasure down in insane asylums, Ku Klux Klan rallies, and finally, the outlaw's hideout.", "poster_path": "/pMI496in22FYw05gOC6nndlPhl8.jpg", "budget": "0", "genres": ["Western", "Comedy"], "vote_average": "0.0", "vote_count": "0", "directors": ["Giuliano Carnimeo"], "actors": ["George Hilton", "Chris Huerta", "Antonio Monselesan", "Memmo Carotenuto", "Nello Pazzafini"]}