{"id": "1581", "title": "The Holiday", "release_date": "2006-12-08", "overview": "Two women, one (Cameron Diaz) from America and one (Kate Winslet) from Britain, swap homes at Christmastime after bad breakups with their boyfriends. Each woman finds romance with a local man (Jude Law, Jack Black) but realizes that the imminent return home may end the relationship.", "poster_path": "/ixNtpuq8OVp4IckgzkSJIflFDkw.jpg", "budget": "85000000", "genres": ["Comedy", "Romance"], "vote_average": "6.7", "vote_count": "1259", "directors": ["Nancy Meyers"], "actors": ["Cameron Diaz", "Kate Winslet", "Jude Law", "Jack Black", "Eli Wallach"]}