{"id": "15834", "title": "Fear Me Not", "release_date": "2008-12-19", "overview": "Michael needs a change in his life, so when he hears about clinical trials for a new anti-depressant, he signs up to be a guinea pig - without telling his family. Because of dangerous side effects, the trial is subsequently abandoned but Michael continues to take the pills. Having lost all control, Michael's repressed instincts resurface with a force and violence that no-one could have predicted.", "poster_path": "/xBBJPyr77jPpKDUH9tsOUTvU52W.jpg", "budget": "0", "genres": ["Drama", "Thriller"], "directors": ["Kristian Levring"], "actors": ["Ulrich Thomsen", "Paprika Steen", "Emma Sehested Høeg", "Lars Brygmann", "Stine Stengade"]}