{"id": "168112", "title": "Eskil & Trinidad", "release_date": "2013-03-29", "overview": "Eskil moves from town to town with his father in Northern Sweden. He misses his mother and sucks at playing hockey, the main activity among the boys his age. Things changes when he meets Trinidad, a mysterious woman who lives outside society spending her time building a great ship that perhaps could take Eskil to his mother...", "poster_path": "/rgO85WKO4dVp5DUfrRlzoSMo6uD.jpg", "budget": "4200000", "genres": ["Drama", "Family"], "vote_average": "5.5", "vote_count": "2", "directors": ["Stephan Apelgren"], "actors": ["Linus Oscarsson", "Ann Petrén", "Torkel Petersson", "Iben Hjejle", "Saga Midfjäll"]}