{"id": "180418", "title": "15 Years and One Day", "release_date": "2013-06-07", "overview": "Jon is a troubled teenager who has been expelled from school. His mother decides to teach him a lesson sending him away with his grandfather Max, a retired military man who lives in a village by the seaside. But the time they will spend together won’t be that simple, Jon likes to flirt with danger and bad companies, and the veteran has now settled down into a comfortable life.", "poster_path": "/iv0XOJw364rd35L8JgChQecqKA3.jpg", "budget": "0", "genres": ["Drama"], "directors": ["Gracia Querejeta"], "actors": ["Maribel Verdú", "Belén López", "Fernando Valverde", "Arón Piper"]}