{"id": "180836", "title": "Miss Marple: The Moving Finger", "release_date": "1985-02-21", "overview": "The residents of a quiet English village begin to receive nasty, threatening letters. The wife of the local vicar calls in her friend Miss Marple to investigate.", "poster_path": "/h5j8WrG9jKBZqTJrWf5UVhy9taT.jpg", "budget": "0", "genres": ["Mystery", "Drama", "Crime"], "directors": ["Roy Boulting"], "actors": ["Joan Hickson", "Michael Culver", "Elizabeth Counsell", "Deborah Appleby", "Lucy Gleeson"]}