{"id": "18187", "title": "Flow: For Love of Water", "release_date": "2008-09-12", "overview": "From both local and global perspectives, this documentary examines the harsh realities behind the mounting water crisis. Learn how politics, pollution and human rights are intertwined in this important issue that affects every being on Earth. With water drying up around the world and the future of human lives at stake, the film urges a call to arms before more of our most precious natural resource evaporates.", "poster_path": "/hRfHHap1vV6rMdZOVMX6ySUpc7M.jpg", "budget": "0", "genres": ["Documentary"], "vote_average": "6.4", "vote_count": "6", "directors": ["Irena Salina"], "actors": []}