{"id": "182228", "title": "100 Degrees Below Zero", "release_date": "2013-03-29", "overview": "After freak climate and weather events destroy the world around them, a group of rogue scientists attempt to reverse the deadly new ice age.", "poster_path": "/98xEqfsOHvTyKqh7Hb4a5USmEPz.jpg", "budget": "500000", "genres": ["Action", "Science Fiction"], "vote_average": "3.6", "vote_count": "23", "directors": ["R.D. Braunstein"], "actors": ["John Rhys-Davies", "Jeff Fahey", "Marc McKevitt Ewins", "Judit Fekete", "Andray Johnson"]}