{"id": "18638", "title": "Faith of My Fathers", "release_date": "2005-05-30", "overview": "Faith of My Fathers is based on the story of Lieutenant Commander John McCain's experiences as a prisoner of war in North Vietnam for five and a half years during the Vietnam War, interleaved with his memories of growing up in a heritage rich with military service.", "poster_path": "/vrb2xzkNvCpUlJypDmU0LLYkpCj.jpg", "budget": "0", "genres": ["War", "Drama"], "vote_average": "6.2", "vote_count": "7", "directors": ["Peter Markle"], "actors": ["Shawn Hatosy", "Scott Glenn", "Erin Cottrell", "Cary-Hiroyuki Tagawa", "Joe Chrest"]}