{"id": "197602", "title": "Death Is a Woman", "release_date": "1966-02-01", "overview": "Narcotics agent Dennis goes undercover in the Mediterranean Islands to investigate a smuggling operation, and gains the confidence of a woman who works for the ringleader. But Dennis ends up arrested for murder when the crime boss turns up dead.", "poster_path": "/13C1XduhsougalKpwbQQutKwvzl.jpg", "budget": "0", "genres": ["Drama", "Mystery"], "directors": ["Frederic Goode"], "actors": ["Trisha Noble", "Mark Burns", "Shaun Curry", "William Dexter", "Wanda Ventham"]}