{"id": "20471", "title": "The Mysteries of Pittsburgh", "release_date": "2008-01-20", "overview": "Based on Michael Chabon's novel, the film chronicles the defining summer of a recent college graduate who crosses his gangster father and explores love, sexuality, and the enigmas surrounding his life and his city.", "poster_path": "/lbSEPULIfAYQhivwMETrbihbsta.jpg", "budget": "0", "genres": ["Adventure", "Comedy", "Drama"], "directors": ["Rawson Marshall Thurber"], "actors": ["Jon Foster", "Peter Sarsgaard", "Sienna Miller", "Nick Nolte", "Mena Suvari"]}