{"id": "211387", "title": "Marvel One-Shot: Agent Carter", "release_date": "2013-09-08", "overview": "The film takes place one year after the events of Captain America: The First Avenger, in which Agent Carter, a member of the Strategic Scientific Reserve, is in search of the mysterious Zodiac.", "poster_path": "/eiw4sh6ieAVuJq6E1bSHQkZPfwm.jpg", "budget": "0", "genres": ["Action", "Adventure", "Science Fiction", "Fantasy"], "vote_average": "7.5", "vote_count": "183", "directors": ["Louis D'Esposito"], "actors": ["Hayley Atwell", "Dominic Cooper", "Greg Haines", "Neal McDonough", "Bradley Whitford"]}