{"id": "212836", "title": "People in Places", "release_date": "2013-12-20", "overview": "This kaleidoscopic film weaves together approximately 20 fragmented scenarios that offer a view of contemporary Spain, drawing conclusions about the persistence of the human condition, strangeness, and the chaos within relationships. Starring Raul Arevalo, Eduard Fernandez and Santiago Segura.", "poster_path": "/96GhOi8G0EfaqJSvjcycthzhwAf.jpg", "budget": "0", "genres": ["Comedy", "Drama"], "directors": ["Juan Cavestany"], "actors": ["Jorge Cabrera", "Tusti de las Heras", "Raquel Guerrero", "David Luque", "Diego Martín"]}