{"id": "21634", "title": "Prayers for Bobby", "release_date": "2009-02-27", "overview": "True story of Mary Griffith, gay rights crusader, whose teenage son committed suicide due to her religious intolerance. Based on the book of the same title by Leroy Aarons.", "poster_path": "/zQGYwsdvabI8uhpyG9S1Hh0qUFr.jpg", "budget": "0", "genres": ["Drama", "History", "TV Movie"], "directors": ["Russell Mulcahy"], "actors": ["Ryan Kelley", "Sigourney Weaver", "Henry Czerny", "Dan Butler", "Austin Nichols"]}