{"id": "239180", "title": "Window Wonderland", "release_date": "2013-11-23", "overview": "With the Christmas season fast approaching, department store window decorator Sloan Van Doren is hoping to take over the recently-vacated head window designer spot but finds she has to prove herself by going up against rival Jake Dooley. As the two compete they find they may have more in common than they think. Stars Chyler Leigh and Naomi Judd.", "poster_path": "/1iMUDVPmFMIbxjoRMlhjrkzwFoV.jpg", "budget": "0", "genres": ["Romance", "Comedy"], "directors": ["Michael Scott"], "actors": ["Chyler Leigh", "Paul Campbell", "Naomi Judd", "Cameron Mathison", "Matty Finochio"]}