{"id": "24331", "title": "Scanners II: The New Order", "release_date": "1991-06-28", "overview": "A scanner discovers a plot by renegade elements in the city government to take power with the help of evil scanners.", "poster_path": "/tp9OVrgTKPkHk165SjLyfwSbnJb.jpg", "budget": "0", "genres": ["Horror", "Science Fiction", "Action"], "vote_average": "4.6", "vote_count": "22", "directors": ["Christian Duguay"], "actors": ["David Hewlett", "Deborah Raffin", "Yvan Ponton", "Isabelle Mejias", "Tom Butler"]}