{"id": "24564", "title": "Radiant City", "release_date": "2007-05-30", "overview": "Since the end of World War II, one of kind of urban residential development has dominate how cities in North America have grown, the suburbs. In these artificial neighborhoods, there is a sense of careless sprawl in an car dominated culture that ineffectually tries to create the more organically grown older communities. Interspersed with the comments of various experts about the nature of suburbia", "poster_path": "/9HrFSlF7quwDCjUar4ckh5ILvxm.jpg", "budget": "0", "genres": ["Documentary"], "vote_average": "7.0", "vote_count": "1", "directors": ["Jim Brown", "Gary Burns"], "actors": ["Hong Cheng", "Kyle Grant", "Amanda Guenther", "Daniel Jeffery", "Mikeala Jeffrey"]}