{"id": "24671", "title": "River Queen", "release_date": "2005-09-12", "overview": "An intimate story set during the 1860s in which a young Irish woman Sarah and her family find themselves on both sides of the turbulent wars between British and Maori during the British colonization of New Zealand.", "poster_path": "/ke8EpGhpUeaIVZOjOoBOfyZ3Bal.jpg", "budget": "0", "genres": ["Adventure", "Drama", "War"], "directors": ["Vincent Ward"], "actors": ["Samantha Morton", "Kiefer Sutherland", "Cliff Curtis", "Stephen Rea", "Temuera Morrison"]}