{"id": "247112", "title": "Smoke on the Potato Fields", "release_date": "1977-10-01", "overview": "In this character study by Czech director Frantisek Vlacil, a stout middle-aged physician whose marriage has come apart establishes a practice in a small town. Gradually he's drawn into the lives of his patients—a childless couple, a pregnant girl with a stern mother, the son of a duck farmer—and each relationship reveals a bit more about him and the idyllic but insular community.", "poster_path": "/7nOQW0vS8uDSC4wU786Ln0Bq7Jv.jpg", "budget": "0", "genres": ["Drama"], "vote_average": "6.0", "vote_count": "1", "directors": ["František Vláčil"], "actors": ["Rudolf Hrušínský", "Věra Galatíková", "Alois Švehlík", "Jana Dítětová", "Vítězslav Jandák"]}