{"id": "261860", "title": "Dior and I", "release_date": "2015-03-27", "overview": "In Frederic Tcheng’s masterful documentary, one enters the storied world that is the House of Christian Dior with a privileged, behind-the-scenes look at the creation of Raf Simons’ first Dior Haute Couture collection as Artistic Director, a true labor of love by a dedicated, charming, and often humorous group of collaborators. Beautifully melding the everyday, pressure-filled components of fashion with a mysterious and elegant reverence for the history of this iconic brand, Tcheng’s colorful homage to the seamstresses of the atelier is nothing short of magical. In English and French with subtitles.", "poster_path": "/9Oua3iTp7E72BXv2vkWvA3JjSpx.jpg", "budget": "0", "genres": ["Documentary"], "directors": ["Frédéric Tcheng"], "actors": ["Marion Cotillard", "Jennifer Lawrence", "Sharon Stone", "Anna Wintour", "Isabelle Huppert"]}