{"id": "2753", "title": "The Assault", "release_date": "1986-02-06", "overview": "At the end of WW II the Dutch resistance kills a German officer in front of the house of a Dutch family. Years after the war the young boy who witnessed the killing runs into the members of the resistance who committed the killing.", "poster_path": "/roLUdrbcpFiWjIqs2NbpItR74KE.jpg", "budget": "0", "genres": ["History", "Drama"], "directors": ["Fons Rademakers"], "actors": ["Derek de Lint", "Marc van Uchelen", "Monique van de Ven", "John Kraaykamp", "Christian Golusda"]}