{"id": "28055", "title": "Blood and Black Lace", "release_date": "1964-03-13", "overview": "Inspector Sylvester is assigned to investigate the violent murder of a fashion house model Isabella, by a masked assailant. As the investigation proceeds all of the house’s various sins, including corruption, abortions, blackmail and drug addiction, begin to come to light. It turns out that Isabella had kept a diary detailing these vices, and now almost every employee becomes nervous.", "poster_path": "/65qKX56J2qGfNBuzmNcoE2WleHI.jpg", "budget": "0", "genres": ["Horror", "Mystery", "Thriller"], "directors": ["Mario Bava"], "actors": ["Cameron Mitchell", "Eva Bartok", "Thomas Reiner", "Ariana Gorini", "Dante DiPaolo"]}