{"id": "287509", "title": "Tokyo Fiancée", "release_date": "2014-09-07", "overview": "A Japanophile young Belgian woman in Tokyo falls into a whirlwind romance with a Francophile Japanese student, in this charming and tender tale of young love and cultural discovery.", "poster_path": "/tCUqK4xHq4vqOayG8jK73b4621f.jpg", "budget": "0", "genres": ["Romance"], "vote_average": "6.0", "vote_count": "32", "directors": ["Stefan Liberski"], "actors": ["Pauline Étienne", "Taichi Inoue", "Julie Le Breton", "Alice de Lencquesaing"]}