{"id": "288183", "title": "A Hole in the Soul", "release_date": "1994-01-01", "overview": "A self-portrait documentary of Dusan Makavejev who travels to former Yugoslavia, and charts the changes of the society which parallels to his own life.", "poster_path": "/p5uTftLWaqgiSJnUNFTU1KWzSnV.jpg", "budget": "0", "genres": ["Documentary"], "vote_average": "0.0", "vote_count": "0", "directors": ["Dusan Makavejev"], "actors": ["Dusan Makavejev", "Rambo Amadeus", "Melodie Annis", "Dennis Jakob", "Paul Yamamoto"]}