{"id": "29383", "title": "The Winter War", "release_date": "1989-12-30", "overview": "Russia attacked Finland in late November 1939. This film tells the story of a Finnish platoon of reservists from the municipality of Kauhava in the province of Pohjanmaa/Ostrobothnia who leave their homes and go to war. The film focuses on the farmer brothers Martti and Paavo Hakala.", "poster_path": "/hoXzrghg8RMtw9ErlWZ6lfixOR9.jpg", "budget": "4414000", "genres": ["Drama", "War"], "directors": ["Pekka Parikka"], "actors": ["Taneli Mäkelä", "Vesa Vierikko", "Timo Torikka", "Heikki Paavilainen", "Antti Raivio"]}