{"id": "30106", "title": "Gunnin' for That #1 Spot", "release_date": "2008-04-18", "overview": "The film follows 8 of the top high school basketball players in the US at the time of filming, in 2006. The plot centers around the first annual Boost Mobile Elite 24 Hoops Classic game at the legendary Rucker Park in Harlem.", "poster_path": "/86qDteN6zqQRcFEa60FfPjLWmf1.jpg", "budget": "0", "genres": ["Documentary"], "directors": ["Adam Yauch"], "actors": ["Jerryd Bayless", "Michael Beasley", "Tyreke Evans", "Donte Greene"]}