{"id": "31347", "title": "Cardcaptor Sakura: The Sealed Card", "release_date": "2000-07-15", "overview": "All of the Clow Cards have been captured, and Sakura Kinomoto, the new Master of the Cards, is preparing to play the lead in the play for the town festival. However, a new evil force is causing mysterious events all over Tomoeda, including the disappearance of Sakura's cards. With Syaoran's help, Sakura must figure out the cause of these events, and save her town.", "poster_path": "/3Qn6L1yE90BCV7djFNFIEdfiKgL.jpg", "budget": "0", "genres": ["Comedy", "Animation", "Adventure", "Fantasy", "Romance"], "directors": ["Morio Asaka"], "actors": ["Sakura Tange", "Kumai Motoko", "Aya Hisakawa", "Masaya Onosaka", "Megumi Ogata"]}