{"id": "315010", "title": "Sense and Sensibility", "release_date": "2008-01-01", "overview": "This is the acclaimed 2008 BBC adaptation of the famous Jane Austen novel. While it originally aired as a 3-part miniseries, this home video release includes a single uninterrupted version of the entire film.", "poster_path": "/5EqkvQ3zqDrtUOh2mIkfJQCzVus.jpg", "budget": "0", "genres": ["Drama"], "vote_average": "7.9", "vote_count": "19", "directors": ["John Alexander"], "actors": ["Hattie Morahan", "Charity Wakefield", "David Morrissey", "Janet McTeer", "Dan Stevens"]}