{"id": "32081", "title": "The Pope of Greenwich Village", "release_date": "1984-06-22", "overview": "Charlie and his troublesome cousin Paulie decide to steal $150000 in order to back a \"sure thing\" race horse that Paulie has inside information on. The aftermath of the robbery gets them into serious trouble with the local Mafia boss and the corrupt New York City police department.", "poster_path": "/k0RJkaPPerN0LZtQKIvxWQgakAF.jpg", "budget": "0", "genres": ["Drama", "Action", "Comedy", "Crime"], "directors": ["Stuart Rosenberg"], "actors": ["Eric Roberts", "Mickey Rourke", "Daryl Hannah", "Geraldine Page", "Kenneth McMillan"]}