{"id": "323373", "title": "Deathgasm", "release_date": "2015-08-28", "overview": "Two teenage boys unwittingly summon an ancient evil entity known as The Blind One by delving into black magic while trying to escape their mundane lives.", "poster_path": "/690lTkTztwK2HLhO9vovXJGeIcQ.jpg", "budget": "0", "genres": ["Comedy", "Horror"], "vote_average": "6.4", "vote_count": "172", "directors": ["Jason Lei Howden"], "actors": ["Milo Cawthorne", "Kimberley Crossman", "Sam Berkley", "Delaney Tabron", "Colin Moy"]}