{"id": "33666", "title": "The Glass Bottom Boat", "release_date": "1966-06-09", "overview": "Bruce (Rod Taylor), the owner of a aerospace company, is infatuated with Jennifer (Doris Day) and hires her to be his biographer so that he can be near her and win her affections. Is she actually a Russian spy trying to obtain aerospace secrets?", "poster_path": "/jlj5rCl7jfW7QskJ1vucd7j5n5M.jpg", "budget": "0", "genres": ["Comedy", "Romance"], "directors": ["Frank Tashlin"], "actors": ["Doris Day", "Rod Taylor", "Arthur Godfrey", "John McGiver", "Paul Lynde"]}