{"id": "339846", "title": "Baywatch", "release_date": "2017-05-12", "overview": "Devoted lifeguard Mitch Buchannon butts heads with a brash new recruit. Together, they uncover a local criminal plot that threatens the future of the Bay.", "poster_path": "/6HE4xd8zloDqmjMZuhUCCw2UcY1.jpg", "budget": "69000000", "genres": ["Action", "Comedy"], "vote_average": "6.1", "vote_count": "1829", "directors": ["Seth Gordon"], "actors": ["Dwayne Johnson", "Zac Efron", "Alexandra Daddario", "Kelly Rohrbach", "Priyanka Chopra"]}