{"id": "340053", "title": "Orson Welles: Shadows & Light", "release_date": "2015-05-09", "overview": "Giant of cinema, the embodiment of creation, Orson Welles is the man who reinvents the film language at 24-years old. Who is hidding behind this impressive figure? This movie is a journey towards the man behind the legend. It drags us into the labyrinth with multiple mirrors that Welles erases and recreates at the mercy of his imagination.", "poster_path": "/tMGPMNAGnuoNIDtyYd7EIDQW6dG.jpg", "budget": "0", "genres": ["Documentary"], "vote_average": "8.0", "vote_count": "1", "directors": ["Elisabeth Kapnist"], "actors": ["Henry Jaglom", "Joseph McBride", "David Thomson"]}