{"id": "35217", "title": "Friendship!", "release_date": "2010-01-13", "overview": "A young man from East Germany travels to San Francisco to search for his father, who fled 12 years ago. Together with his best friend, he starts the journey from New York with no money and the only word they ever learned in english-lessons: \"friendship\".", "poster_path": "/1MjAaqoXUfDkkpAEZLj1xcAVm3d.jpg", "budget": "0", "genres": ["Comedy"], "vote_average": "6.6", "vote_count": "57", "directors": ["Markus Goller"], "actors": ["Matthias Schweighöfer", "Friedrich Mücke", "Alicja Bachleda-Curuś", "Kevin Rankin", "Chris Browning"]}