{"id": "355177", "title": "Tig Notaro: Boyish Girl Interrupted", "release_date": "2015-08-22", "overview": "Known for her distinctive storytelling and offbeat sense of humor, Tig Notaro often draws on her highly personal experiences with no-holds-barred honesty. Over the course of her one-hour show, Notaro tells stories about a number of subjects, including: the search for the perfect Santa Claus; her favorite laugh noises; bringing her fiancée to meet her Mississippi family; TSA screening; flying in small planes; unusual public signs; and more.", "poster_path": "/7e25eDcBOflEBaa6eUooJsNbDMD.jpg", "budget": "0", "genres": ["Comedy"], "directors": ["Jay Karas", "Tig Notaro"], "actors": ["Tig Notaro"]}