{"id": "36298", "title": "Me, Them And Lara", "release_date": "2010-01-01", "overview": "A priest, after spending years in humanitary missions in Africa, reunites with his family, which is in worse conditions than when he left, and above all meets a young lady who will make him doubt both himself and his faith.", "poster_path": "/30gbcgvtnzYIYsk33HMbTv8Sav.jpg", "budget": "0", "genres": ["Comedy", "Drama"], "vote_average": "5.4", "vote_count": "42", "directors": ["Carlo Verdone"], "actors": ["Carlo Verdone", "Laura Chiatti", "Angela Finocchiaro", "Anna Bonaiuto", "Marco Giallini"]}