{"id": "371347", "title": "Marc Maron: More Later", "release_date": "2015-12-04", "overview": "Filmed at The Vic Theatre in Chicago, Marc Maron: More Later captures Maron as he dishes out compelling, raw, and wildly honest stand-up. In this brand new special, Maron tackles religion, relationships, rage, Skype sex and ice cream among other topics in the sheerly authentic way that only he can.", "poster_path": "/ctAlQibS2CM0owRetTUpjxdoeG1.jpg", "budget": "0", "genres": ["Comedy"], "vote_average": "8.1", "vote_count": "5", "directors": ["Bobcat Goldthwait"], "actors": ["Marc Maron"]}