{"id": "37602", "title": "Oysters at Nam Kee's", "release_date": "2002-09-05", "overview": "Young Dutch dropout, Berry, falls in love with slightly older nightclub dancer and ex-nude model Thera and gives up his social live with his dodgy comrades and fine family to make a three-stop 'world tour' together. Suddenly Thera ODs terribly, leaving Berry alone with his obsessive but unanswered love which drives him crazy.", "poster_path": "/67KQ3FNHsjlwuTLFAdfTM81HqIM.jpg", "budget": "0", "genres": ["Drama"], "directors": ["Pollo de Pimentel"], "actors": ["Katja Schuurman", "Egbert Jan Weeber", "Willem Voogd"]}