{"id": "400001", "title": "Trémulo", "release_date": "2015-03-08", "overview": "Carlos sweeps and mops the floor of an old-time barbershop. The day before Independence Day, among the customers is Julio. Their eyes meet, and when the barbershop closes Julio comes back for Carlos. They spend the night together, eating, chatting and even dancing, knowing full well that this encounter will be brief and short-lived.", "poster_path": "/aEE1PjQHjAs3t3lTsHWWNDlbwDQ.jpg", "budget": "0", "genres": ["Romance"], "directors": ["Roberto Fiesco"], "actors": ["Benny Emmanuel", "Axel Arenas", "Alfonso Bravo", "Pascacio López", "Giovanna Zacarías"]}