{"id": "401065", "title": "The Axe Murders of Villisca", "release_date": "2017-01-20", "overview": "Three ghost-hunting high-schoolers visit the Moore House in Villisca, Iowa—the site of one of America’s most grisly unsolved mass murders. After their private tour is interrupted, the group sneaks back in at night, unaware of the otherworldly terror that awaits them.", "poster_path": "/k3qMst5skBFa9Pjyao7Qdwjs9Y0.jpg", "budget": "0", "genres": ["Horror"], "vote_average": "4.9", "vote_count": "16", "directors": ["Tony E. Valenzuela"], "actors": ["Robert Adamson", "Alex Frnka", "Conchata Ferrell", "Jon Gries", "Sean Whalen"]}