{"id": "40577", "title": "Island in the Sky", "release_date": "1953-09-05", "overview": "A C-47 transport plane, named the Corsair, makes a forced landing in the frozen wastes of Labrador, and the plane's pilot, Captain Dooley, must keep his men alive in deadly conditions while waiting for rescue.", "poster_path": "/b82WsrNdU1x0FYCJvNigiN7zYMO.jpg", "budget": "0", "genres": ["Adventure", "Drama"], "vote_average": "6.1", "vote_count": "16", "directors": ["William A. Wellman"], "actors": ["John Wayne", "Lloyd Nolan", "Walter Abel", "James Arness", "Andy Devine"]}