{"id": "44351", "title": "Rabbits", "release_date": "2002-01-01", "overview": "A story of a group of humanoid rabbits and their depressive, daily life. The plot includes Suzie ironing, Jane sitting on a couch, Jack walking in and out of the apartment, and the occasional solo singing number by Suzie or Jane. At one point the rabbits also make contact with their “leader”.", "poster_path": "/u6tDM4uCPGQSOKf0CC9J9DibG9Q.jpg", "budget": "0", "genres": ["Comedy", "Drama", "Fantasy", "Horror"], "vote_average": "7.1", "vote_count": "64", "directors": ["David Lynch"], "actors": ["Scott Coffey", "Rebekah Del Rio", "Laura Harring", "Naomi Watts"]}