{"id": "44800", "title": "The Gambler", "release_date": "1974-10-02", "overview": "New York City English professor Axel Freed outwardly seems like an upstanding citizen. But privately Freed is in the clutches of a severe gambling addiction that threatens to destroy him.", "poster_path": "/ePE6rtrp0hqZllsADhG6uqiysKe.jpg", "budget": "0", "genres": ["Drama", "Crime"], "vote_average": "7.0", "vote_count": "21", "directors": ["Karel Reisz"], "actors": ["James Caan", "Paul Sorvino", "Lauren Hutton", "Morris Carnovsky", "Jacqueline Brookes"]}