{"id": "448847", "title": "The Hatton Garden Job", "release_date": "2017-04-14", "overview": "In April 2015, the Hatton Garden Safe Deposit Company, an underground safe deposit facility in London's Hatton Garden area, was burgled by 4 elderly men. With the stolen property having a value of up to £200 million, the incident has been called the \"largest burglary in English history\".", "poster_path": "/lVBhU6NNMhVPFepF9mwsVbeJG9Y.jpg", "budget": "0", "genres": ["Crime"], "directors": ["Ronnie Thompson"], "actors": ["Matthew Goode", "Joely Richardson", "Larry Lamb", "Phil Daniels", "David Calder"]}