{"id": "45048", "title": "Felicity", "release_date": "1978-10-09", "overview": "Young Felicity lives in a monastic school. The only way to live out her sexual fantasies is together with her girlfriend Jenny. But then she receives an invitation to her sister in Hong-Kong and can't wait to finally do the real thing.", "poster_path": "/w9AEQFE7anO94KvLhM7Om2xqcnK.jpg", "budget": "0", "genres": ["Drama", "Romance"], "directors": ["John D. Lamond"], "actors": ["Glory Annen", "Chris Milne", "Joni Flynn", "Jody Hanson", "Marilyn Rodgers"]}