{"id": "46929", "title": "Fun & Fancy Free", "release_date": "1947-09-27", "overview": "Jiminy Cricket hosts two Disney animated shorts: \"Bongo,\" about a circus bear escaping to the wild, and \"Mickey and the Beanstalk,\" a take on the famous fairy tale.", "poster_path": "/1OuUZOWCSwPSxkZZeArFSA01LlV.jpg", "budget": "0", "genres": ["Animation", "Family", "Music"], "vote_average": "6.2", "vote_count": "64", "directors": ["Jack Kinney", "Hamilton Luske", "William Roberts", "William Morgan"], "actors": ["Edgar Bergen", "Dinah Shore", "Mortimer Snerd", "Luana Patten", "Walt Disney"]}