{"id": "50775", "title": "A Jitney Elopement", "release_date": "1915-04-01", "overview": "Edna's father wants her to marry wealthy Count He-Ha. Charlie, Edna's true love, impersonates the Count at dinner, but the real Count shows up and Charlie is thrown out.", "poster_path": "/rRj1Px6K1mpiDLVbbyQliucxMmb.jpg", "budget": "0", "genres": ["Comedy"], "vote_average": "5.5", "vote_count": "5", "directors": ["Charlie Chaplin"], "actors": ["Charlie Chaplin", "Edna Purviance", "Ernest Van Pelt", "Leo White", "Lloyd Bacon"]}