{"id": "51394", "title": "Night Nurse", "release_date": "1931-07-15", "overview": "Lora Hart manages to land a job in a hospital as a trainee nurse. Upon completion of her training she goes to work as a night nurse for two small children who seem to be very sick, but something much more sinister is going on.", "poster_path": "/jxVxOf0jsyCp7pQi01yWEyj1Zco.jpg", "budget": "0", "genres": ["Crime", "Drama", "Mystery"], "vote_average": "6.2", "vote_count": "17", "directors": ["William A. Wellman"], "actors": ["Barbara Stanwyck", "Ben Lyon", "Joan Blondell", "Clark Gable", "Blanche Friderici"]}