{"id": "5955", "title": "The Pledge", "release_date": "2001-01-09", "overview": "A police chief about to retire pledges to help a woman find her daughter's killer. Based on a story by Swiss writer Friedrich Dürrenmatt.", "poster_path": "/1SLCUsNThBezrLcXHZ7j0t1wRY4.jpg", "budget": "35000000", "genres": ["Crime", "Drama", "Mystery", "Thriller"], "vote_average": "6.6", "vote_count": "221", "directors": ["Sean Penn"], "actors": ["Jack Nicholson", "Aaron Eckhart", "Helen Mirren", "Robin Wright", "Vanessa Redgrave"]}