{"id": "60551", "title": "War Arrow", "release_date": "1954-01-01", "overview": "A thrilling Cavalry-versus-Indians adventure starring Jeff Chandler as an Army official recruiting Seminole allies, against his superior's wishes, to stop a planned Kiowa attack.", "poster_path": "/ghpiljV1gtucFlSQOS5V959SS3y.jpg", "budget": "0", "genres": ["Adventure", "Drama", "Romance", "War", "Western"], "vote_average": "6.4", "vote_count": "6", "directors": ["George Sherman"], "actors": ["Maureen O'Hara", "Jeff Chandler", "John McIntire", "Suzan Ball", "Dennis Weaver"]}