{"id": "617", "title": "Wild Things", "release_date": "1998-03-20", "overview": "When teen-socialite Kelly Van Ryan (Richards) and troubled bad girl Suzie Toller (Campbell) accuse guidance counselor Sam Lombardo (Dillon) of rape, he's suspended by the school, rejected by the town, and fighting to get his life back. One cop (Bacon) suspects conspiracy, but nothing is what it seems...", "poster_path": "/dI9iYo1cL81yzJkBVyNGipjSvy0.jpg", "budget": "20000000", "genres": ["Thriller"], "directors": ["John McNaughton"], "actors": ["Matt Dillon", "Kevin Bacon", "Denise Richards", "Neve Campbell", "Theresa Russell"]}