{"id": "64577", "title": "Summer Affair", "release_date": "1971-04-09", "overview": "A very young Ornella Muti plays a rich girl who falls for an older hippie boy. Her parents don't approve and try to stop her from seeing him so they run away to a villa (Her parents') by the sea. Later they are shipwrecked on a deserted island. The plot focuses on the efforts of the police to figure out where the girl is, which is set against the developing relationship between the two young people.", "poster_path": "/m0CTwz2fEpe5zmhc1g4wkTkMRQk.jpg", "budget": "0", "genres": ["Drama", "Foreign", "Romance"], "directors": ["Giorgio Stegani"], "actors": ["Alessio Orano", "Ornella Muti", "Luigi Pistilli", "Chris Avram", "Roby Ruberti"]}