{"id": "65760", "title": "The Whistleblower", "release_date": "2010-09-13", "overview": "Based on the experiences of Nebraska cop Kathryn Bolkovac (Rachel Weisz) who discovers a deadly sex trafficking ring while serving as a U.N. peacekeeper in post-war Bosnia. Risking her own life to save the lives of others, she uncovers an international conspiracy that is determined to stop her, no matter the cost.", "poster_path": "/vLirzgP5DxW3Ws3z7l2xNQ083TA.jpg", "budget": "0", "genres": ["Drama", "Thriller", "Crime"], "vote_average": "6.6", "vote_count": "157", "directors": ["Larysa Kondracki"], "actors": ["Rachel Weisz", "Vanessa Redgrave", "Monica Bellucci", "David Strathairn", "Nikolaj Lie Kaas"]}