{"id": "709", "title": "Licence to Kill", "release_date": "1989-07-07", "overview": "James Bond and his American colleague Felix Leiter arrest the drug lord Sanchez who succeeds in escaping and takes revenge on Felix and his wife. Bond knows but just one thing: revenge.", "poster_path": "/27EySoBH3oBuI6xat2QOquB9X8j.jpg", "budget": "32000000", "genres": ["Adventure", "Action", "Thriller"], "directors": ["John Glen"], "actors": ["Timothy Dalton", "Carey Lowell", "Robert Davi", "Talisa Soto", "Anthony Zerbe"]}