{"id": "73123", "title": "In Orange", "release_date": "2004-04-28", "overview": "An 11 year old talented soccer player, Remco, has one big dream: to be selected for the national team under 12 years. His father Erik coaches him and everything seems to work out fine, until Erik suddenly dies. Remco and mother Sylvia are shocked. Remco keeps working to fulfil his dream, being helped by his friends Anne and Winston.", "poster_path": "/3bWoJQzqU1BNAFiUYQiuXXDtuKZ.jpg", "budget": "0", "genres": ["Adventure", "Drama", "Family"], "vote_average": "7.0", "vote_count": "6", "directors": ["Joram Lürsen"], "actors": ["Thomas Acda", "Wendy van Dijk", "Yannick van de Velde", "Erik van Muiswinkel", "Peter Blok"]}