{"id": "74008", "title": "Undocumented", "release_date": "2010-09-14", "overview": "A documentary crew accompany a group of illegal immigrants crossing the Border, but their plans run afoul when they are captured by a gang of sadistic radicals in New Mexico.", "poster_path": "/rM8P1nuVGtDSeUWD2l6WjlDTFAA.jpg", "budget": "0", "genres": ["Horror", "Thriller"], "vote_average": "6.6", "vote_count": "10", "directors": ["Chris Peckover"], "actors": ["Scott Mechlowicz", "Alona Tal", "Yancey Arias", "Greg Serano"]}