{"id": "74829", "title": "The Killing of Satan", "release_date": "1983-06-10", "overview": "A Filipino-made horror-fantasy movie about a man who is chosen by his dead uncle to battle the forces of evil. He fights a being called \"The Prince of Magic,\" who shoots rays from his hands, makes heads spin around and hypnotizes people. He finally faces Satan himself and engages him in a battle of magic", "poster_path": "/oxVhiIXw6E2L6SVt3zorxn4fhCG.jpg", "budget": "0", "genres": ["Horror", "Action"], "vote_average": "5.0", "vote_count": "1", "directors": ["Efren C. Piñon"], "actors": ["Ramon Revilla Sr.", "Elizabeth Oropesa", "George Estregan", "Paquito Diaz", "Cecille Castillo"]}