{"id": "7870", "title": "Down in the Valley", "release_date": "2005-05-13", "overview": "On a trip to the beach, a teenage girl named Tobe meets a charismatic stranger named Harlan, who dresses like a cowboy and claims to be a former ranch hand. The pair feel an instant attraction and begin a relationship, but her father, a lawman, is suspicious of her lover.", "poster_path": "/wMlm71hSmvHhNfC6gMOwT1nXsUN.jpg", "budget": "8000000", "genres": ["Drama", "Romance"], "directors": ["David Jacobson"], "actors": ["Edward Norton", "Evan Rachel Wood", "David Morse", "Rory Culkin", "Bruce Dern"]}