{"id": "84562", "title": "Vine of the Soul: Encounters with Ayahuasca", "release_date": "2010-07-23", "overview": "On a quest for emotional healing and spiritual awakening, a naturopathic doctor and an accountant join others in the Peruvian Amazon to drink a psychedelic brew called ayahuasca.", "poster_path": "/gExyhvstQ2yV9sFLFzp0bJd7ZgA.jpg", "budget": "0", "genres": ["Documentary"], "directors": ["Richard Meech"], "actors": ["Guillermo Arévalo", "Gabor Mate", "Dennis J. McKenna", "Kenneth Tupper"]}