{"id": "87169", "title": "The Low Life", "release_date": "1995-11-01", "overview": "John came to Hollywood to get that one big break in life. Years have passed since and all he has to show for are a menial job, unpaid bills and airhead friends and he's getting sick of it all. Is there a way out of this downward spiral?", "poster_path": "/cAz2mr7qsy5rL6eCZDHOe5lD6Bc.jpg", "budget": "0", "genres": [], "vote_average": "6.0", "vote_count": "3", "directors": [], "actors": ["Rory Cochrane", "Sean Astin", "Ron Livingston", "Kyra Sedgwick"]}