{"id": "93", "title": "Anatomy of a Murder", "release_date": "1959-07-01", "overview": "The film pits a humble small-town lawyer against a hard-headed big city prosecutor. Emotions flare as a jealous army lieutenant pleads innocent to murdering the rapist of his seductive, beautiful wife.", "poster_path": "/kDFnM2zlHZirR2ItTo56lyrxuAS.jpg", "budget": "0", "genres": ["Crime", "Drama", "Mystery", "Thriller"], "vote_average": "7.7", "vote_count": "207", "directors": ["Otto Preminger"], "actors": ["James Stewart", "Lee Remick", "Ben Gazzara", "Arthur O'Connell", "Eve Arden"]}