{"id": "9424", "title": "Disturbing Behavior", "release_date": "1998-07-24", "overview": "Steve Clark (James Marsden) is a newcomer in the town of Cradle Bay, and he quickly realizes that there's something odd about his high school classmates. The clique known as the \"Blue Ribbons\" are the eerie embodiment of academic excellence and clean living. But, like the rest of the town, they're a little too perfect. When Steve's rebellious friend Gavin (Nick Stahl) mysteriously joins their ranks, Steve searches for the truth with fellow misfit Rachel (Katie Holmes).", "poster_path": "/8eRU4c5vsCrUT5AyZi9qeRskMWk.jpg", "budget": "15000000", "genres": ["Mystery", "Horror", "Science Fiction"], "vote_average": "5.5", "vote_count": "104", "directors": ["David Nutter"], "actors": ["James Marsden", "Katie Holmes", "Nick Stahl", "Steve Railsback", "Bruce Greenwood"]}