{"id": "9566", "title": "The Fan", "release_date": "1996-08-15", "overview": "When the San Francisco Giants pay centerfielder Bobby Rayburn $40 million to lead their team to the World Series, no one is happier or more supportive than #1 fan Gil Renard.  So when Rayburn becomes mired in the worst slump of his career, the obsessed Renard decides to stop at nothing to help his idol regain his former glory... not even murder.", "poster_path": "/fdW8T9kkYlPyOGh0V5eodFr8SQq.jpg", "budget": "55000000", "genres": ["Drama", "Mystery", "Thriller"], "directors": ["Tony Scott"], "actors": ["Robert De Niro", "Wesley Snipes", "Ellen Barkin", "John Leguizamo", "Benicio del Toro"]}