{"id": "98115", "title": "Harmony and Me", "release_date": "2010-01-15", "overview": "In this indie comedy from helmer Bob Byington, dry wit and deadpan humor abound as aptly named lyricist Harmony (Justin Rice) insists on wallowing in misery eons after being unceremoniously dumped by his girlfriend, the lovely Jessica (Kristen Tucker). While the members of Harmony's family are long over his antics, that doesn't stop him from milking his heartbreak and telling his tale of woe to anyone who will listen.", "poster_path": "/nPIs3OP4VCdPmRdF24pc4qW6ykp.jpg", "budget": "0", "genres": ["Comedy", "Romance"], "vote_average": "5.8", "vote_count": "6", "directors": ["Bob Byington"], "actors": ["Justin Rice", "Alex Karpovsky", "Allison Latta", "Keith Poulson", "Bob Byington"]}